__init__.py
proveit.py
setup.cfg
setup.py
testit.py
proveit.egg-info/PKG-INFO
proveit.egg-info/SOURCES.txt
proveit.egg-info/dependency_links.txt
proveit.egg-info/requires.txt
proveit.egg-info/top_level.txt