Metadata-Version: 1.0
Name: proveit
Version: 0.0.5
Summary: Implementation of gmaxwell's suggestion of proving account balances
Home-page: https://github.com/ConceptPending/proveit
Author: Nick Williamson
Author-email: nick@nickw.info
License: UNKNOWN
Platform: UNKNOWN
